setup.cfg
setup.py
cloud_elements_test_framework/__init__.py
cloud_elements_test_framework.egg-info/PKG-INFO
cloud_elements_test_framework.egg-info/SOURCES.txt
cloud_elements_test_framework.egg-info/dependency_links.txt
cloud_elements_test_framework.egg-info/requires.txt
cloud_elements_test_framework.egg-info/top_level.txt