Metadata-Version: 1.0
Name: cloud-elements-test-framework
Version: 0.0.9
Summary: Cloud Elements Testing Framework for Python
Home-page: https://github.com/cloud-elements/elements-test-framework
Author: Josh Wyse
Author-email: josh@cloud-elements.com
License: UNKNOWN
Keywords: cloud elements
Platform: UNKNOWN
